{
  "_fv": 85,
  "_type": "tool",
  "definition": {
    "toolType": "Axe",
    "renderType": 0,
    "blockingRenderType": 0,
    "texture": "waterfall_crystal_axe",
    "customModelName": "Normal",
    "blockingModelName": "Normal blocking",
    "guiTexture": "waterfall_crystal_axe",
    "name": "Waterfall crystal axe",
    "rarity": "COMMON",
    "specialInformation": {
      "fixedValue": []
    },
    "creativeTabs": [
      {
        "value": "CUSTOM:Undertaletool"
      }
    ],
    "efficiency": 6.5,
    "attackSpeed": 0.9,
    "enchantability": 16,
    "damageVsEntity": 10.0,
    "usageCount": 450,
    "glowCondition": {
      "fixedValue": false
    },
    "repairItems": [
      {
        "value": "CUSTOM:Waterfallcrystal"
      }
    ],
    "immuneToFire": false,
    "blockDropsTier": "IRON",
    "blocksAffected": [],
    "attributeModifiers": [
      {
        "equipmentSlot": "mainhand",
        "attribute": {
          "value": "MOVEMENT_EFFICIENCY"
        },
        "amount": 6.0,
        "operation": "ADD_VALUE"
      }
    ],
    "stayInGridWhenCrafting": false,
    "damageOnCrafting": false
  }
}